setup.cfg
setup.py
Arithemtic_operators_basic.egg-info/PKG-INFO
Arithemtic_operators_basic.egg-info/SOURCES.txt
Arithemtic_operators_basic.egg-info/dependency_links.txt
Arithemtic_operators_basic.egg-info/not-zip-safe
Arithemtic_operators_basic.egg-info/top_level.txt
operators/Arithmetic.py
operators/__init__.py