Metadata-Version: 1.0
Name: Arithemtic-operators-basic
Version: 0.0
Summary: Common arithmetic operators
Home-page: UNKNOWN
Author: UNKNOWN
Author-email: UNKNOWN
License: UNKNOWN
Platform: UNKNOWN
